sparkmagic/__init__.py
sparkmagic/auth/__init__.py
sparkmagic/auth/basic.py
sparkmagic/auth/customauth.py
sparkmagic/auth/kerberos.py
sparkmagic/controllerwidget/__init__.py
sparkmagic/controllerwidget/abstractmenuwidget.py
sparkmagic/controllerwidget/addendpointwidget.py
sparkmagic/controllerwidget/createsessionwidget.py
sparkmagic/controllerwidget/magicscontrollerwidget.py
sparkmagic/controllerwidget/manageendpointwidget.py
sparkmagic/controllerwidget/managesessionwidget.py
sparkmagic/kernels/__init__.py
sparkmagic/kernels/kernelmagics.py
sparkmagic/kernels/pysparkkernel/__init__.py
sparkmagic/kernels/pysparkkernel/kernel.js
sparkmagic/kernels/pysparkkernel/kernel.json
sparkmagic/kernels/pysparkkernel/pysparkkernel.py
sparkmagic/kernels/sparkkernel/__init__.py
sparkmagic/kernels/sparkkernel/kernel.js
sparkmagic/kernels/sparkkernel/kernel.json
sparkmagic/kernels/sparkkernel/sparkkernel.py
sparkmagic/kernels/sparkrkernel/__init__.py
sparkmagic/kernels/sparkrkernel/kernel.js
sparkmagic/kernels/sparkrkernel/kernel.json
sparkmagic/kernels/sparkrkernel/sparkrkernel.py
sparkmagic/kernels/wrapperkernel/__init__.py
sparkmagic/kernels/wrapperkernel/sparkkernelbase.py
sparkmagic/kernels/wrapperkernel/usercodeparser.py
sparkmagic/livyclientlib/__init__.py
sparkmagic/livyclientlib/command.py
sparkmagic/livyclientlib/configurableretrypolicy.py
sparkmagic/livyclientlib/endpoint.py
sparkmagic/livyclientlib/exceptions.py
sparkmagic/livyclientlib/linearretrypolicy.py
sparkmagic/livyclientlib/livyreliablehttpclient.py
sparkmagic/livyclientlib/livysession.py
sparkmagic/livyclientlib/reliablehttpclient.py
sparkmagic/livyclientlib/sendpandasdftosparkcommand.py
sparkmagic/livyclientlib/sendstringtosparkcommand.py
sparkmagic/livyclientlib/sendtosparkcommand.py
sparkmagic/livyclientlib/sessionmanager.py
sparkmagic/livyclientlib/sparkcontroller.py
sparkmagic/livyclientlib/sparkstorecommand.py
sparkmagic/livyclientlib/sqlquery.py
sparkmagic/magics/__init__.py
sparkmagic-0.23.0.dist-info/METADATA
sparkmagic-0.23.0.dist-info/WHEEL
sparkmagic-0.23.0.dist-info/top_level.txt
sparkmagic-0.23.0.dist-info/RECORD
