Metadata-Version: 2.1
Name: sparkmagic
Version: 0.23.0
Summary: SparkMagic: Spark execution via Livy
Home-page: https://github.com/jupyter-incubator/sparkmagic
Download-URL: https://github.com/jupyter-incubator/sparkmagic
Author: Jupyter Development Team
Author-email: jupyter@googlegroups.org
License: BSD 3-clause
Classifier: Development Status :: 4 - Beta
Classifier: Environment :: Console
Classifier: Intended Audience :: Science/Research
Classifier: License :: OSI Approved :: BSD License
Classifier: Natural Language :: English
Classifier: Programming Language :: Python :: 3.7
Requires-Dist: hdijupyterutils >=0.6
Requires-Dist: autovizwidget >=0.6
Requires-Dist: ipython >=4.1.2
Requires-Dist: pandas <3.0.0
Requires-Dist: numpy
Requires-Dist: requests
Requires-Dist: ipykernel >=4.2.2
Requires-Dist: ipywidgets >5.0.0
Requires-Dist: notebook >=4.2
Requires-Dist: tornado >=4
Requires-Dist: requests-kerberos >=0.8.0
Requires-Dist: nest-asyncio >1.5.5
